BioExp
