Metadata-Version: 2.1
Name: BioExp
Version: 0.0.3
Summary: Deep Learning model analysis toolbox
Home-page: https://github.com/koriavinash1/BioExp
Author: Avinash Kori, Parth Natekar
Author-email: koriavinash1@gmail.com, parth@smail.iitm.ac.in
License: UNKNOWN
Platform: UNKNOWN
Classifier: Programming Language :: Python :: 3.5
Classifier: License :: OSI Approved :: MIT License
Classifier: Operating System :: OS Independent
